wiko/__init__.py
wiko/generate_download_area.py
wiko/generate_figures.py
wiko/generate_gallery.py
wiko/runtests.py
wiko/tex2wiki.py
wiko/wiko.py
wiko/wiko_util.py
wiko-1.0.0.dist-info/METADATA
wiko-1.0.0.dist-info/WHEEL
wiko-1.0.0.dist-info/entry_points.txt
wiko-1.0.0.dist-info/top_level.txt
wiko-1.0.0.dist-info/RECORD
