Metadata-Version: 2.1
Name: wiko
Version: 1.0.0
Summary: WiKo: The wiki compiler, a static site and pdf generator.
Author: Natanael Olaiz
Author-email: David García Garzón <voki@canvoki.net>, Pau Arumí Albò <pau.arumi@dolby.com>
Project-URL: Homepage, https://github.com/clam-project/wiko
Project-URL: Bug Tracker, https://github.com/clam-project/wiko/issues
Keywords: Static site generator,Wiki
Classifier: Development Status :: 7 - Inactive
Classifier: License :: OSI Approved :: GNU Affero General Public License v3 or later (AGPLv3+)
Classifier: Natural Language :: English
Classifier: Operating System :: OS Independent
Classifier: Programming Language :: Python
Classifier: Programming Language :: Python :: 3.8
Classifier: Programming Language :: Python :: 3.9
Classifier: Topic :: Internet :: WWW/HTTP :: Dynamic Content :: Wiki
Classifier: Topic :: Internet :: WWW/HTTP :: Dynamic Content :: Content Management System
Requires-Python: >=3.8
Requires-Dist: gdata-python3
Requires-Dist: pyside6
Requires-Dist: utidylib
Requires-Dist: pygments
Requires-Dist: pillow
